setup.py
src/JsQt.egg-info/PKG-INFO
src/JsQt.egg-info/SOURCES.txt
src/JsQt.egg-info/dependency_links.txt
src/JsQt.egg-info/entry_points.txt
src/JsQt.egg-info/requires.txt
src/JsQt.egg-info/top_level.txt
src/jsqt/__init__.py
src/jsqt/base.py
src/jsqt/entry_points.py
src/jsqt/parser.py
src/jsqt/xml.py
src/jsqt/il/__init__.py
src/jsqt/il/primitive.py
src/jsqt/il/qt/__init__.py
src/jsqt/il/qt/bar.py
src/jsqt/il/qt/base.py
src/jsqt/il/qt/container.py
src/jsqt/il/qt/form.py
src/jsqt/il/qt/gui.py
src/jsqt/il/qt/itemview.py
src/jsqt/il/qt/layout.py
src/jsqt/il/qt/obj.py
src/jsqt/js/__init__.py
src/jsqt/js/primitive.py