Metadata-Version: 1.0
Name: JsQt
Version: 0.5.0
Summary: A tool to compile Qt Designer's .ui files to qooxdoo code.
Home-page: http://jsqt.org
Author: Burak Arslan
Author-email: burak-jsqt@arskom.com.tr
License: GPLv2
Platform: Linux
Platform: Mac OSX
Platform: Windows 7/Vista/XP/2000/NT
Platform: Windows 95/98/ME
